mcp_neo4j_knowledge_graph/__init__.py
mcp_neo4j_knowledge_graph/mcp/server.py
mcp_neo4j_knowledge_graph/mcp/tools/create_entities.py
mcp_neo4j_knowledge_graph/mcp/tools/create_relations.py
mcp_neo4j_knowledge_graph/mcp/tools/delete_entities.py
mcp_neo4j_knowledge_graph/mcp/tools/introspect_schema.py
mcp_neo4j_knowledge_graph/mcp/tools/search_entities.py
mcp_neo4j_knowledge_graph/mcp/tools/update_entities.py
mcp_neo4j_knowledge_graph/neo4j/driver.py
mcp_neo4j_knowledge_graph/neo4j/operations/create_entities.py
mcp_neo4j_knowledge_graph/neo4j/operations/create_relations.py
mcp_neo4j_knowledge_graph/neo4j/operations/delete_entities.py
mcp_neo4j_knowledge_graph/neo4j/operations/introspect_schema.py
mcp_neo4j_knowledge_graph/neo4j/operations/search_entities.py
mcp_neo4j_knowledge_graph/neo4j/operations/update_entities.py
mcp_neo4j_knowledge_graph/test_mcp_client.py
mcp_neo4j_knowledge_graph/test_mcp_config.py
mcp_neo4j_knowledge_graph/test_neo4j_connection.py
iflow_mcp_mjftw_neo4j_mcp_server-0.1.0.dist-info/METADATA
iflow_mcp_mjftw_neo4j_mcp_server-0.1.0.dist-info/WHEEL
iflow_mcp_mjftw_neo4j_mcp_server-0.1.0.dist-info/entry_points.txt
iflow_mcp_mjftw_neo4j_mcp_server-0.1.0.dist-info/RECORD
