Metadata-Version: 2.4
Name: iflow-mcp_mjftw_neo4j-mcp-server
Version: 0.1.0
Summary: A Memory Control Protocol server implementation using Neo4j as the backend storage for knowledge graph management
Author: Merlin Webster mjftwebster@gmail.com
Requires-Python: >=3.11,<3.14
Classifier: Programming Language :: Python :: 3
Classifier: Programming Language :: Python :: 3.11
Classifier: Programming Language :: Python :: 3.12
Classifier: Programming Language :: Python :: 3.13
Requires-Dist: fastapi (>=0.109.2,<0.110.0)
Requires-Dist: fastmcp (>=0.4.1,<0.5.0)
Requires-Dist: mcp (==1.6.0)
Requires-Dist: neo4j (>=5.15.0,<6.0.0)
Requires-Dist: pydantic (>=2.6.1,<3.0.0)
Requires-Dist: python-dotenv (>=1.0.1,<2.0.0)
Requires-Dist: uvicorn (>=0.27.1,<0.28.0)
